iSTAGING_Workshop/__init__.py
iSTAGING_Workshop/cli.py
iSTAGING_Workshop/train_test_model.py
iSTAGING_Workshop-0.1.1.dist-info/LICENSE
iSTAGING_Workshop-0.1.1.dist-info/METADATA
iSTAGING_Workshop-0.1.1.dist-info/WHEEL
iSTAGING_Workshop-0.1.1.dist-info/entry_points.txt
iSTAGING_Workshop-0.1.1.dist-info/top_level.txt
iSTAGING_Workshop-0.1.1.dist-info/RECORD
