Metadata-Version: 2.1
Name: iSTAGING_Workshop
Version: 0.1.1
Summary: Example package for the iSTAGING Workshop
Home-page: https://github.com/georgeaidinis/iSTAGING_Workshop
Download-URL: https://github.com/georgeaidinis/iSTAGING_Workshop/archive/refs/tags/v0.1.zip
Author: George Aidinis
Author-email: George.Aidinis@Pennmedicine.upenn.edu
Maintainer: George Aidinis
Maintainer-email: George.Aidinis@pennmedicine.upenn.edu
Project-URL: Bug Tracker, https://github.com/georgeaidinis/iSTAGING_workshop/issues
Keywords: medical image analysis
Classifier: Programming Language :: Python :: 3
Classifier: Operating System :: OS Independent
Classifier: Intended Audience :: Developers
Classifier: Intended Audience :: Science/Research
Classifier: Intended Audience :: Healthcare Industry
Classifier: Programming Language :: Python :: 3
Classifier: Topic :: Scientific/Engineering :: Artificial Intelligence
Requires-Python: >=3.8
License-File: LICENSE
Requires-Dist: numpy
Requires-Dist: pandas
Requires-Dist: scikit-learn
Requires-Dist: spare-scores
